{
  "generated": "2026-07-14T17:23:13.647437Z",
  "tomtom": [
    {
      "source": "TomTom",
      "kind": "Traffic Jam",
      "severity": "minor",
      "desc": "Slow traffic",
      "from": "New Port Richey",
      "to": "Mile Stretch Dr",
      "roadnums": "US-19 S",
      "roads": [
        "US 19"
      ],
      "delay_sec": 84,
      "length_m": 130.738,
      "coords": [
        28.1885522733,
        -82.7400367574
      ]
    },
    {
      "source": "TomTom",
      "kind": "Traffic Jam",
      "severity": "moderate",
      "desc": "Backed up traffic",
      "from": "New Port Richey",
      "to": "Darlington Rd",
      "roadnums": "",
      "roads": [],
      "delay_sec": 93,
      "length_m": 164.5198566414,
      "coords": [
        28.1938684697,
        -82.7399120347
      ]
    },
    {
      "source": "TomTom",
      "kind": "Traffic Jam",
      "severity": "moderate",
      "desc": "Backed up traffic",
      "from": "New Port Richey",
      "to": "Moog Rd",
      "roadnums": "US-19 N",
      "roads": [
        "US 19"
      ],
      "delay_sec": 93,
      "length_m": 147.8622545944,
      "coords": [
        28.2088647008,
        -82.739621015
      ]
    },
    {
      "source": "TomTom",
      "kind": "Traffic Jam",
      "severity": "minor",
      "desc": "Slow traffic",
      "from": "New Port Richey",
      "to": "Grand Blvd",
      "roadnums": "FL-54",
      "roads": [],
      "delay_sec": 67,
      "length_m": 144.2451578488,
      "coords": [
        28.2170253129,
        -82.7219144122
      ]
    },
    {
      "source": "TomTom",
      "kind": "Road Closed",
      "severity": "closure",
      "desc": "Closed",
      "from": "Aspen St",
      "to": "Grand Blvd",
      "roadnums": "",
      "roads": [],
      "delay_sec": null,
      "length_m": 158.7983712618,
      "coords": [
        28.2361628496,
        -82.7220512048
      ]
    },
    {
      "source": "TomTom",
      "kind": "Road Closed",
      "severity": "closure",
      "desc": "Closed",
      "from": "Grand Blvd",
      "to": "Aspen St",
      "roadnums": "",
      "roads": [],
      "delay_sec": null,
      "length_m": 158.7983712618,
      "coords": [
        28.2361628496,
        -82.7220512048
      ]
    },
    {
      "source": "TomTom",
      "kind": "Traffic Jam",
      "severity": "minor",
      "desc": "Slow traffic",
      "from": "New Port Richey",
      "to": "Madison St",
      "roadnums": "FL-54",
      "roads": [],
      "delay_sec": 54,
      "length_m": 145.8132968764,
      "coords": [
        28.217041414,
        -82.7163448051
      ]
    },
    {
      "source": "TomTom",
      "kind": "Road Closed",
      "severity": "closure",
      "desc": "Closed",
      "from": "Mapleton Ln / Monarch Dr",
      "to": "Morehead Ln / Saybrook Dr",
      "roadnums": "",
      "roads": [],
      "delay_sec": null,
      "length_m": 177.055902901,
      "coords": [
        28.294694039,
        -82.6759641484
      ]
    },
    {
      "source": "TomTom",
      "kind": "Traffic Jam",
      "severity": "major",
      "desc": "Stopped traffic",
      "from": "Paddock Ln",
      "to": "Northwinder Row",
      "roadnums": "",
      "roads": [],
      "delay_sec": 158,
      "length_m": 244.0294241373,
      "coords": [
        28.3371466624,
        -82.6761103288
      ]
    },
    {
      "source": "TomTom",
      "kind": "Traffic Jam",
      "severity": "major",
      "desc": "Stopped traffic",
      "from": "Little Rd",
      "to": "Ridge Rd",
      "roadnums": "",
      "roads": [
        "Little Road",
        "Ridge Road"
      ],
      "delay_sec": 263,
      "length_m": 199.901247382,
      "coords": [
        28.2786946176,
        -82.6749851421
      ]
    },
    {
      "source": "TomTom",
      "kind": "Traffic Jam",
      "severity": "moderate",
      "desc": "Backed up traffic",
      "from": "US Highway 19",
      "to": "Penwood Way",
      "roadnums": "",
      "roads": [
        "US 19"
      ],
      "delay_sec": 143,
      "length_m": 470.2522869295,
      "coords": [
        28.4257829548,
        -82.6480799035
      ]
    },
    {
      "source": "TomTom",
      "kind": "Road Closed",
      "severity": "closure",
      "desc": "Closed",
      "from": "W Lutz Lake Fern Rd",
      "to": "W Lutz Lake Fern Rd",
      "roadnums": "",
      "roads": [],
      "delay_sec": null,
      "length_m": 39.1190238243,
      "coords": [
        28.1606050398,
        -82.5336059049
      ]
    },
    {
      "source": "TomTom",
      "kind": "Road Closed",
      "severity": "closure",
      "desc": "Closed",
      "from": "W Lutz Lake Fern Rd",
      "to": "W Lutz Lake Fern Rd",
      "roadnums": "",
      "roads": [],
      "delay_sec": null,
      "length_m": 39.1190238243,
      "coords": [
        28.1606291303,
        -82.5335012988
      ]
    },
    {
      "source": "TomTom",
      "kind": "Traffic Jam",
      "severity": "major",
      "desc": "Stopped traffic",
      "from": "Hale Rd (US-41)",
      "to": "FL-54 (US-41)",
      "roadnums": "FL-45 US-41 S",
      "roads": [],
      "delay_sec": 163,
      "length_m": 490.508062349,
      "coords": [
        28.193164372,
        -82.4655461922
      ]
    },
    {
      "source": "TomTom",
      "kind": "Traffic Jam",
      "severity": "major",
      "desc": "Stopped traffic",
      "from": "Central Pasco",
      "to": "Pleasant Plains Pkwy",
      "roadnums": "",
      "roads": [],
      "delay_sec": 221,
      "length_m": 180.5036710196,
      "coords": [
        28.2817778476,
        -82.4445377901
      ]
    },
    {
      "source": "TomTom",
      "kind": "Traffic Jam",
      "severity": "moderate",
      "desc": "Backed up traffic",
      "from": "Livingston Rd",
      "to": "Livingston Rd",
      "roadnums": "FL-54",
      "roads": [],
      "delay_sec": 60,
      "length_m": 232.4399715588,
      "coords": [
        28.1859478974,
        -82.4341858044
      ]
    },
    {
      "source": "TomTom",
      "kind": "Traffic Jam",
      "severity": "minor",
      "desc": "Slow traffic",
      "from": "Central Pasco",
      "to": "Livingston Rd",
      "roadnums": "FL-54",
      "roads": [],
      "delay_sec": 65,
      "length_m": 126.905205149,
      "coords": [
        28.1859934811,
        -82.4282353237
      ]
    },
    {
      "source": "TomTom",
      "kind": "Traffic Jam",
      "severity": "moderate",
      "desc": "Backed up traffic",
      "from": "State Road 54",
      "to": "State Road 54",
      "roadnums": "",
      "roads": [
        "SR 54"
      ],
      "delay_sec": 58,
      "length_m": 213.6744318525,
      "coords": [
        28.1858754213,
        -82.407822372
      ]
    },
    {
      "source": "TomTom",
      "kind": "Road Closed",
      "severity": "closure",
      "desc": "Closed",
      "from": "Wesley Chapel Blvd",
      "to": "Compark Dr / Scarborough Dr",
      "roadnums": "",
      "roads": [],
      "delay_sec": null,
      "length_m": 55.9480836986,
      "coords": [
        28.2237925064,
        -82.3808916524
      ]
    },
    {
      "source": "TomTom",
      "kind": "Road Closed",
      "severity": "closure",
      "desc": "Closed",
      "from": "Compark Dr / Scarborough Dr",
      "to": "Wesley Chapel Blvd",
      "roadnums": "",
      "roads": [],
      "delay_sec": null,
      "length_m": 55.9480836986,
      "coords": [
        28.2237925064,
        -82.3808916524
      ]
    },
    {
      "source": "TomTom",
      "kind": "Traffic Jam",
      "severity": "moderate",
      "desc": "Backed up traffic",
      "from": "Cypress Glen Dr",
      "to": "Tanic Dr",
      "roadnums": "",
      "roads": [],
      "delay_sec": 59,
      "length_m": 99.3261728037,
      "coords": [
        28.1915577324,
        -82.372545959
      ]
    },
    {
      "source": "TomTom",
      "kind": "Traffic Jam",
      "severity": "moderate",
      "desc": "Stopped traffic",
      "from": "Old Pasco Rd",
      "to": "Wesley Chapel Blvd",
      "roadnums": "",
      "roads": [],
      "delay_sec": 61,
      "length_m": 65.4019376834,
      "coords": [
        28.2380055615,
        -82.3667805508
      ]
    },
    {
      "source": "TomTom",
      "kind": "Traffic Jam",
      "severity": "moderate",
      "desc": "Stopped traffic",
      "from": "Central Pasco",
      "to": "Bellamy Brothers Blvd",
      "roadnums": "FL-52",
      "roads": [],
      "delay_sec": 100,
      "length_m": 167.252086934,
      "coords": [
        28.3243699858,
        -82.3590477422
      ]
    },
    {
      "source": "TomTom",
      "kind": "Traffic Jam",
      "severity": "major",
      "desc": "Stopped traffic",
      "from": "Wiregrass Ranch Blvd",
      "to": "State Road 54",
      "roadnums": "",
      "roads": [
        "SR 54"
      ],
      "delay_sec": 214,
      "length_m": 149.0272945017,
      "coords": [
        28.2359684156,
        -82.3426379874
      ]
    },
    {
      "source": "TomTom",
      "kind": "Road Closed",
      "severity": "closure",
      "desc": "Closed",
      "from": "Mansfield Blvd",
      "to": "Mansfield Blvd / Oakwood Preserve Dr",
      "roadnums": "",
      "roads": [],
      "delay_sec": null,
      "length_m": 382.3999595584,
      "coords": [
        28.1895420112,
        -82.322395356
      ]
    },
    {
      "source": "TomTom",
      "kind": "Road Closed",
      "severity": "closure",
      "desc": "Closed",
      "from": "McKendree Rd",
      "to": "Corporate Lake Blvd / McKendree Rd",
      "roadnums": "FL-52",
      "roads": [],
      "delay_sec": null,
      "length_m": 117.8528307608,
      "coords": [
        28.3250633304,
        -82.3073387757
      ]
    },
    {
      "source": "TomTom",
      "kind": "Road Closed",
      "severity": "closure",
      "desc": "Closed",
      "from": "Pacente Loop",
      "to": "Hillman Ct",
      "roadnums": "",
      "roads": [],
      "delay_sec": null,
      "length_m": 129.791009896,
      "coords": [
        28.2117601254,
        -82.2712094202
      ]
    },
    {
      "source": "TomTom",
      "kind": "Road Closed",
      "severity": "closure",
      "desc": "Closed",
      "from": "Pompanic St",
      "to": "Joe Herrmann Dr",
      "roadnums": "",
      "roads": [],
      "delay_sec": null,
      "length_m": 129.0366073473,
      "coords": [
        28.3362468251,
        -82.2715768829
      ]
    },
    {
      "source": "TomTom",
      "kind": "Traffic Jam",
      "severity": "major",
      "desc": "Stopped traffic",
      "from": "FL-54 (Morris Bridge Rd)",
      "to": "FL-56 (Morris Bridge Rd)",
      "roadnums": "",
      "roads": [
        "Ridge Road"
      ],
      "delay_sec": 198,
      "length_m": 444.7404255417,
      "coords": [
        28.210227259,
        -82.2460784629
      ]
    },
    {
      "source": "TomTom",
      "kind": "Traffic Jam",
      "severity": "major",
      "desc": "Stopped traffic",
      "from": "Handcart Rd (Eiland Blvd/CR-54)",
      "to": "Dean Dairy Rd (Eiland Blvd/CR-54)",
      "roadnums": "County Hwy-54",
      "roads": [],
      "delay_sec": 185,
      "length_m": 812.8308601914,
      "coords": [
        28.2445809938,
        -82.2154838457
      ]
    },
    {
      "source": "TomTom",
      "kind": "Traffic Jam",
      "severity": "major",
      "desc": "Stopped traffic",
      "from": "CR-579/Morris Bridge Rd (FL-56)",
      "to": "US-301/Gall Blvd (FL-56)",
      "roadnums": "FL-56",
      "roads": [
        "Ridge Road"
      ],
      "delay_sec": 144,
      "length_m": 404.4658224972,
      "coords": [
        28.1941393662,
        -82.2032020106
      ]
    },
    {
      "source": "TomTom",
      "kind": "Traffic Jam",
      "severity": "major",
      "desc": "Stopped traffic",
      "from": "US Highway 98 Byp",
      "to": "7th St",
      "roadnums": "",
      "roads": [],
      "delay_sec": 180,
      "length_m": 152.3970493808,
      "coords": [
        28.3638615016,
        -82.1882205322
      ]
    },
    {
      "source": "TomTom",
      "kind": "Traffic Jam",
      "severity": "major",
      "desc": "Stopped traffic",
      "from": "Tollar Rd (FL-39)",
      "to": "County Line Rd (FL-39)",
      "roadnums": "FL-39",
      "roads": [
        "County Line Road"
      ],
      "delay_sec": 235,
      "length_m": 2053.2225243453,
      "coords": [
        28.1545606679,
        -82.1527805045
      ]
    }
  ],
  "fhp": [
    {
      "source": "FHP",
      "kind": "Hit and Run Crash",
      "severity": "reported",
      "desc": "Hit and Run Crash",
      "location": "38815 CUMMER RD   [DADE CITY]",
      "county": "PASCO",
      "roads": [],
      "coords": [
        28.4574143302591,
        -82.1752373718072
      ]
    },
    {
      "source": "FHP",
      "kind": "VEHICLE CRASH W/INJURIES AND ROADBLOCK",
      "severity": "reported",
      "desc": "VEHICLE CRASH W/INJURIES AND ROADBLOCK",
      "location": "SR-54 x[EVANS ST]    [ZEPHYRHILLS]",
      "county": "PASCO",
      "roads": [
        "SR 54"
      ],
      "coords": [
        28.2299733377251,
        -82.2070292010517
      ]
    },
    {
      "source": "FHP",
      "kind": "Vehicle Crash w/roadblock",
      "severity": "reported",
      "desc": "Vehicle Crash w/roadblock",
      "location": "8270 RIDGE RD   [PORT RICHEY]",
      "county": "PASCO",
      "roads": [
        "Ridge Road"
      ],
      "coords": [
        28.2805103996487,
        -82.6781653809682
      ]
    },
    {
      "source": "FHP",
      "kind": "Vehicle Crash",
      "severity": "reported",
      "desc": "Vehicle Crash",
      "location": "BRUCE B DOWNS BLVD x[EAGLESTON BLVD]    [WESLEY CHAPEL]",
      "county": "PASCO",
      "roads": [],
      "coords": [
        28.2214009661836,
        -82.3532649118283
      ]
    },
    {
      "source": "FHP",
      "kind": "VEHICLE CRASH W/INJURIES AND ROADBLOCK",
      "severity": "reported",
      "desc": "VEHICLE CRASH W/INJURIES AND ROADBLOCK",
      "location": "8270 RIDGE RD   [PORT RICHEY]",
      "county": "PASCO",
      "roads": [
        "Ridge Road"
      ],
      "coords": [
        28.2804774615722,
        -82.678134289705
      ]
    }
  ],
  "monitored_roads_active": [
    "County Line Road",
    "Little Road",
    "Ridge Road",
    "SR 54",
    "US 19"
  ],
  "overlap": [
    "Ridge Road",
    "SR 54"
  ]
}